{
  "metadata": {
    "episode": 40,
    "timestamp": 1766439984.644943,
    "dimensions": 2,
    "total_nodes": 32
  },
  "config": {
    "federation": {
      "num_holons": 4,
      "world_bounds": [
        1.0,
        1.0
      ],
      "breach_threshold": 0.1,
      "coordination_mode": "positional",
      "enable_dynamic_splitting": false
    },
    "holon": {
      "mode": "training",
      "independent_training": true,
      "share_experience": false,
      "use_r_gnn": false
    },
    "node": {
      "total_nodes": 32,
      "num_nodes_per_holon": 8,
      "move_speed": 0.01,
      "sensor_range": 0.15
    },
    "spatial": {
      "dimensions": 2,
      "world_bounds": [
        1.0,
        1.0
      ]
    },
    "gnn": {
      "hidden_dim": 128,
      "num_layers": 3,
      "n_heads": 4,
      "lr": 0.0001,
      "gamma": 0.98,
      "dropout": 0.1,
      "buffer_capacity": 15000
    },
    "loop": {
      "ideal_distance": 0.12,
      "stiffness": 0.45,
      "break_threshold": 0.3
    },
    "rewards": {
      "r_flow": 2.0,
      "r_collision": 35.0,
      "r_idle": 1.0,
      "r_loop_integrity": 10.0,
      "r_collapse_penalty": 30.0,
      "r_explore": 10.0,
      "r_reconnection_spatial": 35.0,
      "r_reconnection_temporal": 10.0,
      "r_boundary_breach": 5.0
    },
    "repulsion": {
      "local_grid_size": [
        5,
        5
      ],
      "global_grid_shape": [
        60,
        60
      ],
      "eta": 0.5,
      "gamma_f": 0.9,
      "k_f": 5,
      "sigma_f": 0.05,
      "decay_lambda": 0.9,
      "blur_delta": 0.1,
      "beta": 0.3
    },
    "exploration": {
      "map_resolution": 0.01,
      "sensor_range": 0.15
    },
    "wfc": {
      "history_length": 150,
      "tail_length": 8,
      "collapse_threshold": 0.55,
      "tau": 2,
      "spatial_search_radius_mult": 0.9,
      "spatial_samples": 32,
      "spatial_accept_threshold": 0.65,
      "spatial_improvement_min": 0.999
    },
    "obstacles": [
      [
        0.229,
        0.257,
        0.008
      ],
      [
        0.329,
        0.186,
        0.008
      ],
      [
        0.286,
        0.143,
        0.008
      ],
      [
        0.071,
        0.429,
        0.008
      ],
      [
        0.029,
        0.208,
        0.008
      ],
      [
        0.029,
        0.657,
        0.008
      ],
      [
        0.129,
        0.786,
        0.008
      ],
      [
        0.486,
        0.843,
        0.008
      ],
      [
        0.071,
        0.882,
        0.008
      ],
      [
        0.629,
        0.257,
        0.008
      ],
      [
        0.829,
        0.486,
        0.008
      ],
      [
        0.986,
        0.143,
        0.008
      ],
      [
        0.571,
        0.429,
        0.008
      ],
      [
        0.729,
        0.208,
        0.008
      ],
      [
        0.629,
        0.557,
        0.008
      ],
      [
        0.749,
        0.786,
        0.008
      ],
      [
        0.986,
        0.643,
        0.008
      ],
      [
        0.571,
        0.829,
        0.008
      ],
      [
        0.729,
        0.908,
        0.008
      ]
    ],
    "moving_obstacles": [],
    "training": {
      "num_episodes": 40,
      "steps_per_episode": 500,
      "target_update_frequency": 100,
      "save_frequency": 100,
      "metrics_save_frequency": 20
    },
    "visualization": {
      "show_partitions": true,
      "show_breach_alerts": true,
      "partition_color_scheme": "rainbow",
      "render_frequency": 50,
      "save_history": true
    }
  },
  "nodes": [
    {
      "id": 0,
      "holon_id": 0,
      "pos": [
        0.44008374876522616,
        0.18801614973932967
      ],
      "last_pos": [
        0.8802419633171428,
        0.38591317999240193
      ],
      "dimensions": 2,
      "sensor_range": 0.15,
      "move_speed": 0.01
    },
    {
      "id": 1,
      "holon_id": 0,
      "pos": [
        0.42589888091870787,
        0.24821632550598802
      ],
      "last_pos": [
        0.8517445419168589,
        0.5066157714404399
      ],
      "dimensions": 2,
      "sensor_range": 0.15,
      "move_speed": 0.01
    },
    {
      "id": 2,
      "holon_id": 0,
      "pos": [
        0.47741045200903226,
        0.21729610535947202
      ],
      "last_pos": [
        0.9547857035580966,
        0.44452629626219015
      ],
      "dimensions": 2,
      "sensor_range": 0.15,
      "move_speed": 0.01
    },
    {
      "id": 3,
      "holon_id": 0,
      "pos": [
        0.44058009891390026,
        0.17074750263854788
      ],
      "last_pos": [
        0.8811326787034522,
        0.35191599800742374
      ],
      "dimensions": 2,
      "sensor_range": 0.15,
      "move_speed": 0.01
    },
    {
      "id": 4,
      "holon_id": 0,
      "pos": [
        0.4293433779405486,
        0.22594732507009246
      ],
      "last_pos": [
        0.8586450279487885,
        0.46141629221430186
      ],
      "dimensions": 2,
      "sensor_range": 0.15,
      "move_speed": 0.01
    },
    {
      "id": 5,
      "holon_id": 0,
      "pos": [
        0.38815934497153504,
        0.18448210878989885
      ],
      "last_pos": [
        0.776435836325072,
        0.37908332908888553
      ],
      "dimensions": 2,
      "sensor_range": 0.15,
      "move_speed": 0.01
    },
    {
      "id": 6,
      "holon_id": 0,
      "pos": [
        0.40911524615560657,
        0.24076115454376054
      ],
      "last_pos": [
        0.8181682011546076,
        0.49152094639680594
      ],
      "dimensions": 2,
      "sensor_range": 0.15,
      "move_speed": 0.01
    },
    {
      "id": 7,
      "holon_id": 0,
      "pos": [
        0.46973268931376,
        0.23931919452088954
      ],
      "last_pos": [
        0.939493725052615,
        0.488579918933509
      ],
      "dimensions": 2,
      "sensor_range": 0.15,
      "move_speed": 0.01
    },
    {
      "id": 8,
      "holon_id": 1,
      "pos": [
        0.7172222424390852,
        0.08281594169273247
      ],
      "last_pos": [
        0.4348378687081844,
        0.15552287370685886
      ],
      "dimensions": 2,
      "sensor_range": 0.15,
      "move_speed": 0.01
    },
    {
      "id": 9,
      "holon_id": 1,
      "pos": [
        0.9402565888071419,
        0.20479620816495353
      ],
      "last_pos": [
        0.892444248165994,
        0.4146890995439195
      ],
      "dimensions": 2,
      "sensor_range": 0.15,
      "move_speed": 0.01
    },
    {
      "id": 10,
      "holon_id": 1,
      "pos": [
        0.90068185928683,
        0.09567562627271212
      ],
      "last_pos": [
        0.8070145264902862,
        0.18921404993646324
      ],
      "dimensions": 2,
      "sensor_range": 0.15,
      "move_speed": 0.01
    },
    {
      "id": 11,
      "holon_id": 1,
      "pos": [
        0.9696602748538905,
        0.021211714169061154
      ],
      "last_pos": [
        0.9366775433890395,
        0.030522611694183282
      ],
      "dimensions": 2,
      "sensor_range": 0.15,
      "move_speed": 0.01
    },
    {
      "id": 12,
      "holon_id": 1,
      "pos": [
        0.580591839052724,
        0.49233352518865114
      ],
      "last_pos": [
        0.1666049123320581,
        0.9824274387666928
      ],
      "dimensions": 2,
      "sensor_range": 0.15,
      "move_speed": 0.01
    },
    {
      "id": 13,
      "holon_id": 1,
      "pos": [
        0.5775694754550392,
        0.35768039198090773
      ],
      "last_pos": [
        0.15572447077991525,
        0.7159639991126012
      ],
      "dimensions": 2,
      "sensor_range": 0.15,
      "move_speed": 0.01
    },
    {
      "id": 14,
      "holon_id": 1,
      "pos": [
        0.6140286185859971,
        0.332831304420343
      ],
      "last_pos": [
        0.23711161092595257,
        0.6662403413393972
      ],
      "dimensions": 2,
      "sensor_range": 0.15,
      "move_speed": 0.01
    },
    {
      "id": 15,
      "holon_id": 1,
      "pos": [
        0.7660657500263397,
        0.06289549247929874
      ],
      "last_pos": [
        0.5417381162226653,
        0.12589999463720355
      ],
      "dimensions": 2,
      "sensor_range": 0.15,
      "move_speed": 0.01
    },
    {
      "id": 16,
      "holon_id": 2,
      "pos": [
        0.4080864607837045,
        0.9741058935551427
      ],
      "last_pos": [
        0.816753101938821,
        0.9407624187778936
      ],
      "dimensions": 2,
      "sensor_range": 0.15,
      "move_speed": 0.01
    },
    {
      "id": 17,
      "holon_id": 2,
      "pos": [
        0.40923317798707093,
        0.9132423798625244
      ],
      "last_pos": [
        0.8184691420951734,
        0.8162826574141848
      ],
      "dimensions": 2,
      "sensor_range": 0.15,
      "move_speed": 0.01
    },
    {
      "id": 18,
      "holon_id": 2,
      "pos": [
        0.3517201800330898,
        0.5515322076079417
      ],
      "last_pos": [
        0.6945031015680031,
        0.10179465899612428
      ],
      "dimensions": 2,
      "sensor_range": 0.15,
      "move_speed": 0.01
    },
    {
      "id": 19,
      "holon_id": 2,
      "pos": [
        0.30246509244420344,
        0.6103818466908777
      ],
      "last_pos": [
        0.5938674433865834,
        0.2220334496015146
      ],
      "dimensions": 2,
      "sensor_range": 0.15,
      "move_speed": 0.01
    },
    {
      "id": 20,
      "holon_id": 2,
      "pos": [
        0.449099906619566,
        0.5185617577297088
      ],
      "last_pos": [
        0.8869877743616862,
        0.03658815663518622
      ],
      "dimensions": 2,
      "sensor_range": 0.15,
      "move_speed": 0.01
    },
    {
      "id": 21,
      "holon_id": 2,
      "pos": [
        0.4066236423325352,
        0.5
      ],
      "last_pos": [
        0.8041531104153217,
        0.0
      ],
      "dimensions": 2,
      "sensor_range": 0.15,
      "move_speed": 0.01
    },
    {
      "id": 22,
      "holon_id": 2,
      "pos": [
        0.46516704191125346,
        0.5269446846210044
      ],
      "last_pos": [
        0.9198442000163773,
        0.053587648280673195
      ],
      "dimensions": 2,
      "sensor_range": 0.15,
      "move_speed": 0.01
    },
    {
      "id": 23,
      "holon_id": 2,
      "pos": [
        0.42124747967412624,
        0.5034716978866592
      ],
      "last_pos": [
        0.8327080897891329,
        0.005038424069185199
      ],
      "dimensions": 2,
      "sensor_range": 0.15,
      "move_speed": 0.01
    },
    {
      "id": 24,
      "holon_id": 3,
      "pos": [
        0.8694032041731947,
        0.8514631292647838
      ],
      "last_pos": [
        0.7369496337192831,
        0.6970980917167273
      ],
      "dimensions": 2,
      "sensor_range": 0.15,
      "move_speed": 0.01
    },
    {
      "id": 25,
      "holon_id": 3,
      "pos": [
        0.9668194715847006,
        0.8880431356894067
      ],
      "last_pos": [
        0.9375712696090224,
        0.7674655229693801
      ],
      "dimensions": 2,
      "sensor_range": 0.15,
      "move_speed": 0.01
    },
    {
      "id": 26,
      "holon_id": 3,
      "pos": [
        0.6314096697965258,
        0.7976529424643002
      ],
      "last_pos": [
        0.2528193395930516,
        0.5953058849286004
      ],
      "dimensions": 2,
      "sensor_range": 0.15,
      "move_speed": 0.01
    },
    {
      "id": 27,
      "holon_id": 3,
      "pos": [
        0.7503370317352094,
        0.7109772954420305
      ],
      "last_pos": [
        0.5033226210986208,
        0.43209413555771325
      ],
      "dimensions": 2,
      "sensor_range": 0.15,
      "move_speed": 0.01
    },
    {
      "id": 28,
      "holon_id": 3,
      "pos": [
        0.7822477491459258,
        0.7140585059711773
      ],
      "last_pos": [
        0.5642995753956748,
        0.4353068310630275
      ],
      "dimensions": 2,
      "sensor_range": 0.15,
      "move_speed": 0.01
    },
    {
      "id": 29,
      "holon_id": 3,
      "pos": [
        0.7238634861692769,
        0.8132366270212319
      ],
      "last_pos": [
        0.4286278082417512,
        0.5830377298870568
      ],
      "dimensions": 2,
      "sensor_range": 0.15,
      "move_speed": 0.01
    },
    {
      "id": 30,
      "holon_id": 3,
      "pos": [
        0.7606160860206472,
        0.7119282018613595
      ],
      "last_pos": [
        0.5221621564712924,
        0.43152929771503024
      ],
      "dimensions": 2,
      "sensor_range": 0.15,
      "move_speed": 0.01
    },
    {
      "id": 31,
      "holon_id": 3,
      "pos": [
        0.8252165097752883,
        0.7283937548525821
      ],
      "last_pos": [
        0.6487998419628882,
        0.4613405624523623
      ],
      "dimensions": 2,
      "sensor_range": 0.15,
      "move_speed": 0.01
    }
  ],
  "holons": [
    {
      "holon_id": 0,
      "x_min": 0.0,
      "x_max": 0.5,
      "y_min": 0.0,
      "y_max": 0.5,
      "center": [
        0.25,
        0.25
      ]
    },
    {
      "holon_id": 1,
      "x_min": 0.5,
      "x_max": 1.0,
      "y_min": 0.0,
      "y_max": 0.5,
      "center": [
        0.75,
        0.25
      ]
    },
    {
      "holon_id": 2,
      "x_min": 0.0,
      "x_max": 0.5,
      "y_min": 0.5,
      "y_max": 1.0,
      "center": [
        0.25,
        0.75
      ]
    },
    {
      "holon_id": 3,
      "x_min": 0.5,
      "x_max": 1.0,
      "y_min": 0.5,
      "y_max": 1.0,
      "center": [
        0.75,
        0.75
      ]
    }
  ]
}